jupyterlab_fold_all_code_extension/__init__.py
jupyterlab_fold_all_code_extension/_version.py
jupyterlab_fold_all_code_extension/preprocessor.py
jupyterlab_fold_all_code_extension-1.0.35.data/data/etc/jupyter/jupyter_nbconvert_config.json
jupyterlab_fold_all_code_extension-1.0.35.data/data/etc/jupyter/jupyter_server_config.d/jupyterlab_fold_all_code_extension.json
jupyterlab_fold_all_code_extension-1.0.35.data/data/share/jupyter/labextensions/jupyterlab_fold_all_code_extension/package.json
jupyterlab_fold_all_code_extension-1.0.35.data/data/share/jupyter/labextensions/jupyterlab_fold_all_code_extension/static/509.3483bbb687f3a0428bf7.js
jupyterlab_fold_all_code_extension-1.0.35.data/data/share/jupyter/labextensions/jupyterlab_fold_all_code_extension/static/728.908b95923664cc97b687.js
jupyterlab_fold_all_code_extension-1.0.35.data/data/share/jupyter/labextensions/jupyterlab_fold_all_code_extension/static/remoteEntry.df76b568e3225dc8f7d2.js
jupyterlab_fold_all_code_extension-1.0.35.data/data/share/jupyter/labextensions/jupyterlab_fold_all_code_extension/static/style.js
jupyterlab_fold_all_code_extension-1.0.35.data/data/share/jupyter/labextensions/jupyterlab_fold_all_code_extension/static/third-party-licenses.json
jupyterlab_fold_all_code_extension-1.0.35.data/data/share/jupyter/labextensions/jupyterlab_fold_all_code_extension/install.json
jupyterlab_fold_all_code_extension-1.0.35.dist-info/METADATA
jupyterlab_fold_all_code_extension-1.0.35.dist-info/WHEEL
jupyterlab_fold_all_code_extension-1.0.35.dist-info/entry_points.txt
jupyterlab_fold_all_code_extension-1.0.35.dist-info/licenses/LICENSE
jupyterlab_fold_all_code_extension-1.0.35.dist-info/RECORD
