Metadata-Version: 2.4
Name: jupyterlab_fold_all_code_extension
Version: 1.0.35
Summary: Jupyterlab extension to fold and expand all code cells, to help create nice notebook to share with non-technical audience
Project-URL: Homepage, https://github.com/stellarshenson/jupyterlab_fold_all_code_extension
Project-URL: Bug Tracker, https://github.com/stellarshenson/jupyterlab_fold_all_code_extension/issues
Project-URL: Repository, https://github.com/stellarshenson/jupyterlab_fold_all_code_extension.git
Author-email: Stellars Henson <konrad.jelen@gmail.com>
License: BSD 3-Clause License
License-File: LICENSE
Keywords: jupyter,jupyterlab,jupyterlab-extension
Classifier: Framework :: Jupyter
Classifier: Framework :: Jupyter :: JupyterLab
Classifier: Framework :: Jupyter :: JupyterLab :: 4
Classifier: Framework :: Jupyter :: JupyterLab :: Extensions
Classifier: Framework :: Jupyter :: JupyterLab :: Extensions :: Prebuilt
Classifier: License :: OSI Approved :: BSD License
Classifier: Programming Language :: Python
Classifier: Programming Language :: Python :: 3
Classifier: Programming Language :: Python :: 3.10
Classifier: Programming Language :: Python :: 3.11
Classifier: Programming Language :: Python :: 3.12
Classifier: Programming Language :: Python :: 3.13
Classifier: Programming Language :: Python :: 3.14
Requires-Python: >=3.10
Requires-Dist: nbconvert>=6.0
